{
  "id": "gc",
  "title": "Guerre Cognitive",
  "cat": "Fondamental",
  "tags": [
    "doctrine",
    "fondamentaux"
  ],
  "xp": 25,
  "short": "Stratégie ciblant le cerveau pour altérer le traitement de l'information.",
  "body": "<h3>Définition</h3><p>Utilise les technologies pour influencer ou perturber la cognition. Cible les processus subconscients.</p><h3>Distinction</h3><p>Info = contrôle des données. Cognitive = altération du <em>processing</em>.</p><h3>Trois piliers</h3><ul><li><strong>Effets cognitifs</strong> (biais)</li><li><strong>Hostilité asymétrique</strong> (zone grise)</li><li><strong>Amplification techno</strong> (IA/Big Data)</li></ul>"
}